amyg.py
amyg-0.1.7.dist-info/licenses/LICENSE
amyg-0.1.7.dist-info/METADATA
amyg-0.1.7.dist-info/WHEEL
amyg-0.1.7.dist-info/entry_points.txt
amyg-0.1.7.dist-info/top_level.txt
amyg-0.1.7.dist-info/RECORD
