Metadata-Version: 2.4
Name: amyg
Version: 0.1.7
Summary: A pipeline for De Novo Genomic Annotation of Non-Model Organisms compatible with Single Cell RNA-seq
Home-page: https://github.com/cfarkas/amyg
Author: Carlos Farkas
Author-email: carlosfarkas@gmail.com
License: MIT
Classifier: Programming Language :: Python :: 3
Classifier: License :: OSI Approved :: MIT License
Classifier: Operating System :: OS Independent
Requires-Python: >=3.7
License-File: LICENSE
Dynamic: author
Dynamic: author-email
Dynamic: classifier
Dynamic: description
Dynamic: description-content-type
Dynamic: home-page
Dynamic: license
Dynamic: license-file
Dynamic: requires-python
Dynamic: summary
